<?xml version="1.0" ?>
<Notes>

<Note time="2783" level="1">left</Note>
<Note time="3880" level="1">right</Note>
<Note time="5126" level="1">left</Note>
<Note time="6367" level="1">right</Note>
<Note time="7607" level="1">left</Note>
<Note time="8822" level="1">right</Note>
<Note time="10058" level="1">left</Note>
<Note time="11309" level="1">right</Note>
<Note time="12591" level="1">left</Note>
<Note time="12918" level="1">right</Note>
<Note time="13227" level="1">left</Note>
<Note time="13507" level="1">right</Note>
<Note time="15050" level="1">left</Note>
<Note time="15348" level="1">right</Note>
<Note time="15666" level="1">left</Note>
<Note time="15971" level="1">right</Note>
<Note time="17663" level="1">left</Note>
<Note time="17762" level="1">right</Note>
<Note time="18082" level="1">left</Note>
<Note time="18370" level="1">right</Note>
<Note time="19945" level="1">left</Note>
<Note time="20242" level="1">right</Note>
<Note time="20545" level="1">left</Note>
<Note time="20848" level="1">right</Note>
<Note time="22391" level="1">left</Note>
<Note time="23063" level="1">right</Note>
<Note time="23646" level="1">left</Note>
<Note time="24256" level="1">right</Note>
<Note time="24583" level="1">left</Note>
<Note time="24927" level="1">right</Note>
<Note time="25214" level="1">left</Note>
<Note time="25535" level="1">right</Note>
<Note time="25815" level="1">left</Note>
<Note time="26111" level="1">right</Note>
<Note time="27903" level="1">left</Note>
<Note time="28199" level="1">right</Note>
<Note time="29127" level="1">left</Note>
<Note time="29430" level="1">right</Note>
<Note time="32206" level="1">left</Note>
<Note time="32525" level="1">right</Note>
<Note time="34037" level="1">left</Note>
<Note time="34350" level="1">right</Note>
<Note time="37852" level="1">left</Note>
<Note time="38154" level="1">right</Note>
<Note time="39111" level="1">left</Note>
<Note time="39404" level="1">right</Note>
<Note time="42817" level="1">left</Note>
<Note time="43140" level="1">right</Note>
<Note time="44043" level="1">left</Note>
<Note time="44316" level="1">right</Note>
<Note time="46538" level="1">left</Note>
<Note time="47146" level="1">right</Note>
<Note time="47755" level="1">left</Note>
<Note time="48333" level="1">right</Note>
<Note time="48955" level="1">left</Note>
<Note time="49554" level="1">right</Note>
<Note time="50122" level="1">left</Note>
<Note time="50802" level="1">right</Note>
<Note time="56319" level="1">left</Note>
<Note time="56663" level="1">right</Note>
<Note time="56991" level="1">left</Note>
<Note time="57304" level="1">right</Note>
<Note time="57639" level="1">left</Note>
<Note time="57975" level="1">right</Note>
<Note time="58279" level="1">left</Note>
<Note time="58607" level="1">right</Note>
<Note time="61236" level="1">left</Note>
<Note time="61533" level="1">right</Note>
<Note time="62439" level="1">left</Note>
<Note time="62757" level="1">right</Note>
<Note time="66141" level="1">left</Note>
<Note time="66443" level="1">right</Note>
<Note time="67372" level="1">left</Note>
<Note time="67661" level="1">right</Note>
<Note time="71074" level="1">left</Note>
<Note time="71386" level="1">right</Note>
<Note time="72305" level="1">left</Note>
<Note time="72578" level="1">right</Note>
<Note time="75991" level="1">left</Note>
<Note time="76296" level="1">right</Note>
<Note time="77238" level="1">left</Note>
<Note time="77531" level="1">right</Note>
<Note time="80327" level="1">left</Note>
<Note time="80655" level="1">right</Note>
<Note time="80967" level="1">left</Note>
<Note time="82736" level="1">right</Note>
<Note time="83071" level="1">left</Note>
<Note time="83400" level="1">right</Note>
<Note time="84006" level="1">left</Note>
<Note time="84615" level="1">right</Note>
<Note time="85232" level="1">left</Note>
<Note time="85887" level="1">right</Note>
<Note time="86462" level="1">left</Note>
<Note time="87111" level="1">right</Note>
<Note time="87719" level="1">left</Note>
<Note time="88662" level="1">right</Note>
<Note time="88982" level="1">left</Note>
<Note time="89301" level="1">right</Note>
<Note time="89774" level="1">left</Note>
<Note time="89902" level="1">right</Note>
<Note time="90189" level="1">left</Note>
<Note time="90478" level="1">right</Note>
<Note time="90759" level="1">left</Note>
<Note time="91094" level="1">right</Note>
<Note time="91414" level="1">left</Note>
<Note time="91831" level="1">right</Note>
<Note time="91997" level="1">left</Note>
<Note time="92269" level="1">right</Note>
<Note time="92597" level="1">left</Note>
<Note time="92875" level="1">right</Note>
<Note time="93211" level="1">left</Note>
<Note time="93603" level="1">right</Note>
<Note time="93947" level="1">left</Note>
<Note time="94291" level="1">right</Note>
<Note time="94579" level="1">left</Note>
<Note time="95066" level="1">right</Note>
<Note time="95667" level="1">left</Note>
<Note time="96292" level="1">right</Note>
<Note time="96866" level="1">left</Note>


</Notes>